LICENSE.txt
MANIFEST.in
README.md
setup.py
jk_vcard/QuotedPrintable.py
jk_vcard/VCFEncoder.py
jk_vcard/VCFParser.py
jk_vcard/VCFToken.py
jk_vcard/VCFTokenizer.py
jk_vcard/VCard.py
jk_vcard/VCardItem.py
jk_vcard/__init__.py
jk_vcard.egg-info/PKG-INFO
jk_vcard.egg-info/SOURCES.txt
jk_vcard.egg-info/dependency_links.txt
jk_vcard.egg-info/not-zip-safe
jk_vcard.egg-info/requires.txt
jk_vcard.egg-info/top_level.txt