Metadata-Version: 2.1
Name: jk-vcard
Version: 0.2020.9.21.1
Summary: This python module parses (and produces) vCard data as provided in vcf files.
Home-page: https://github.com/jkpubsrc/python-module-jk-vcard
Author: Jürgen Knauth
Author-email: pubsrc@binary-overflow.de
License: Apache 2.0
Download-URL: https://github.com/jkpubsrc/python-module-jk-vcard/tarball/0.2020.9.21
Keywords: vcard,vcf
Platform: UNKNOWN
Classifier: Development Status :: 3 - Alpha
Classifier: License :: OSI Approved :: Apache Software License
